resource_id/__init__.py
resource_id/py.typed
resource_id/resource_id.py
resource_id-1.4.0.dist-info/licenses/LICENSE.txt
resource_id-1.4.0.dist-info/METADATA
resource_id-1.4.0.dist-info/WHEEL
resource_id-1.4.0.dist-info/top_level.txt
resource_id-1.4.0.dist-info/RECORD
