Metadata-Version: 2.4
Name: resource-id
Version: 1.4.0
Summary: A base62-encoded identifier for use in URLs.  Supports Pydantic validation.
Author-email: Charles Yeomans <charles@declaresub.com>
License-Expression: MIT
Project-URL: Homepage, https://github.com/declaresub/resource-id
Keywords: identifier,url,base62,uuid,fastapi
Classifier: Development Status :: 5 - Production/Stable
Classifier: Intended Audience :: Developers
Classifier: Topic :: Internet :: WWW/HTTP :: HTTP Servers
Classifier: Framework :: FastAPI
Classifier: Programming Language :: Python
Classifier: Programming Language :: Python :: 3
Classifier: Programming Language :: Python :: 3.9
Classifier: Programming Language :: Python :: 3.10
Classifier: Programming Language :: Python :: 3.11
Classifier: Programming Language :: Python :: 3.12
Classifier: Programming Language :: Python :: 3.13
Classifier: Typing :: Typed
License-File: LICENSE.txt
Requires-Dist: pydantic>=2
Requires-Dist: typing_extensions>=4.6.0; python_version < "3.10"
Dynamic: license-file
